lleidaseeker/__init__.py
lleidaseeker/lleidaseeker.cpython-36-linux.so
lleidaseeker/lleidaseeker.py
lleidaseeker/bin/coll-linux
lleidaseeker/scripts/seekeragg.sh
lleidaseeker-0.0.1.dist-info/AUTHORS.rst
lleidaseeker-0.0.1.dist-info/LICENSE.rst
lleidaseeker-0.0.1.dist-info/METADATA
lleidaseeker-0.0.1.dist-info/WHEEL
lleidaseeker-0.0.1.dist-info/top_level.txt
lleidaseeker-0.0.1.dist-info/RECORD
