Metadata-Version: 2.1
Name: lleidaseeker
Version: 0.0.1
Summary: InsideOpt Seeker Centos 7 Linux 36 Distribution
Author: Meinolf Sellmann
Author-email: info@insideopt.com
Keywords: insideopt,seeker,optimization
Classifier: Development Status :: 5 - Production/Stable
Classifier: Intended Audience :: Developers
Classifier: Natural Language :: English
Classifier: Programming Language :: Python :: 3.6
Classifier: Operating System :: POSIX :: Linux
Requires-Python: >=3.6.0
License-File: LICENSE.rst
License-File: AUTHORS.rst
